{
  "id": "f049e7c0-47ee-4913-b59c-b8db0693b8a3",
  "realm": "internet-shop",
  "notBefore": 0,
  "defaultSignatureAlgorithm": "RS256",
  "revokeRefreshToken": false,
  "refreshTokenMaxReuse": 0,
  "accessTokenLifespan": 300,
  "accessTokenLifespanForImplicitFlow": 900,
  "ssoSessionIdleTimeout": 1800,
  "ssoSessionMaxLifespan": 36000,
  "ssoSessionIdleTimeoutRememberMe": 0,
  "ssoSessionMaxLifespanRememberMe": 0,
  "offlineSessionIdleTimeout": 2592000,
  "offlineSessionMaxLifespanEnabled": false,
  "offlineSessionMaxLifespan": 5184000,
  "clientSessionIdleTimeout": 0,
  "clientSessionMaxLifespan": 0,
  "clientOfflineSessionIdleTimeout": 0,
  "clientOfflineSessionMaxLifespan": 0,
  "accessCodeLifespan": 60,
  "accessCodeLifespanUserAction": 300,
  "accessCodeLifespanLogin": 1800,
  "actionTokenGeneratedByAdminLifespan": 43200,
  "actionTokenGeneratedByUserLifespan": 300,
  "oauth2DeviceCodeLifespan": 600,
  "oauth2DevicePollingInterval": 5,
  "enabled": true,
  "sslRequired": "external",
  "registrationAllowed": false,
  "registrationEmailAsUsername": false,
  "rememberMe": false,
  "verifyEmail": false,
  "loginWithEmailAllowed": true,
  "duplicateEmailsAllowed": false,
  "resetPasswordAllowed": false,
  "editUsernameAllowed": false,
  "bruteForceProtected": false,
  "permanentLockout": false,
  "maxTemporaryLockouts": 0,
  "bruteForceStrategy": "MULTIPLE",
  "maxFailureWaitSeconds": 900,
  "minimumQuickLoginWaitSeconds": 60,
  "waitIncrementSeconds": 60,
  "quickLoginCheckMilliSeconds": 1000,
  "maxDeltaTimeSeconds": 43200,
  "failureFactor": 30,
  "roles": {
    "realm": [
      {
        "id": "66b8fbe6-f182-492e-8226-2e4821048fbe",
        "name": "default-roles-internet-shop",
        "description": "${role_default-roles}",
        "composite": true,
        "composites": {
          "realm": [
            "offline_access",
            "uma_authorization"
          ],
          "client": {
            "account": [
              "manage-account",
              "view-profile"
            ]
          }
        },
        "clientRole": false,
        "containerId": "f049e7c0-47ee-4913-b59c-b8db0693b8a3",
        "attributes": {}
      },
      {
        "id": "c61d4196-319b-4f29-91dd-89dfcb09e26e",
        "name": "uma_authorization",
        "description": "${role_uma_authorization}",
        "composite": false,
        "clientRole": false,
        "containerId": "f049e7c0-47ee-4913-b59c-b8db0693b8a3",
        "attributes": {}
      },
      {
        "id": "427b16f2-7a8d-42b2-8707-f1a9ac47e6c4",
        "name": "offline_access",
        "description": "${role_offline-access}",
        "composite": false,
        "clientRole": false,
        "containerId": "f049e7c0-47ee-4913-b59c-b8db0693b8a3",
        "attributes": {}
      },
      {
        "id": "419dc012-0133-47a4-9e88-a5678aa427a2",
        "name": "USER",
        "description": "Just an ordinary user of the shop.",
        "composite": false,
        "clientRole": false,
        "containerId": "f049e7c0-47ee-4913-b59c-b8db0693b8a3",
        "attributes": {}
      },
      {
        "id": "3bbb01fc-2142-4515-aad0-ccdae3d41a95",
        "name": "ADMIN",
        "description": "Only with this role it's possible to add products to the shop.",
        "composite": false,
        "clientRole": false,
        "containerId": "f049e7c0-47ee-4913-b59c-b8db0693b8a3",
        "attributes": {}
      }
    ],
    "client": {
      "main_module": [],
      "realm-management": [
        {
          "id": "6c00fb52-5744-4b8c-985c-99a526a1c4e2",
          "name": "query-users",
          "description": "${role_query-users}",
          "composite": false,
          "clientRole": true,
          "containerId": "6d24261c-a344-44a5-8d3e-aed7f8672294",
          "attributes": {}
        },
        {
          "id": "9e0c0261-5db4-4f77-af1f-5f39322a2d91",
          "name": "manage-realm",
          "description": "${role_manage-realm}",
          "composite": false,
          "clientRole": true,
          "containerId": "6d24261c-a344-44a5-8d3e-aed7f8672294",
          "attributes": {}
        },
        {
          "id": "41ad1f9c-701e-41d0-b9ec-8de67143978e",
          "name": "query-clients",
          "description": "${role_query-clients}",
          "composite": false,
          "clientRole": true,
          "containerId": "6d24261c-a344-44a5-8d3e-aed7f8672294",
          "attributes": {}
        },
        {
          "id": "9d831ae9-278c-4f0c-a23a-e6ee8975c4e6",
          "name": "view-realm",
          "description": "${role_view-realm}",
          "composite": false,
          "clientRole": true,
          "containerId": "6d24261c-a344-44a5-8d3e-aed7f8672294",
          "attributes": {}
        },
        {
          "id": "7a554492-a9d9-48d2-ac58-de331185fd0c",
          "name": "manage-events",
          "description": "${role_manage-events}",
          "composite": false,
          "clientRole": true,
          "containerId": "6d24261c-a344-44a5-8d3e-aed7f8672294",
          "attributes": {}
        },
        {
          "id": "91116508-8196-4053-b180-9503aac97e61",
          "name": "impersonation",
          "description": "${role_impersonation}",
          "composite": false,
          "clientRole": true,
          "containerId": "6d24261c-a344-44a5-8d3e-aed7f8672294",
          "attributes": {}
        },
        {
          "id": "7f26af4d-0488-4fbd-99c9-11ed7304c080",
          "name": "query-realms",
          "description": "${role_query-realms}",
          "composite": false,
          "clientRole": true,
          "containerId": "6d24261c-a344-44a5-8d3e-aed7f8672294",
          "attributes": {}
        },
        {
          "id": "d8b524b2-8086-42d2-ac5d-d94e67e1823c",
          "name": "view-identity-providers",
          "description": "${role_view-identity-providers}",
          "composite": false,
          "clientRole": true,
          "containerId": "6d24261c-a344-44a5-8d3e-aed7f8672294",
          "attributes": {}
        },
        {
          "id": "49c32df4-dadb-4cb6-b978-f301756d496c",
          "name": "manage-users",
          "description": "${role_manage-users}",
          "composite": false,
          "clientRole": true,
          "containerId": "6d24261c-a344-44a5-8d3e-aed7f8672294",
          "attributes": {}
        },
        {
          "id": "c87e81d8-a72c-43e0-af65-2b69a2c92aac",
          "name": "view-clients",
          "description": "${role_view-clients}",
          "composite": true,
          "composites": {
            "client": {
              "realm-management": [
                "query-clients"
              ]
            }
          },
          "clientRole": true,
          "containerId": "6d24261c-a344-44a5-8d3e-aed7f8672294",
          "attributes": {}
        },
        {
          "id": "f0bcd424-d07f-4b3c-b3c9-f90d157576eb",
          "name": "create-client",
          "description": "${role_create-client}",
          "composite": false,
          "clientRole": true,
          "containerId": "6d24261c-a344-44a5-8d3e-aed7f8672294",
          "attributes": {}
        },
        {
          "id": "c87f2238-2b0c-45b8-8c19-38bf142c6515",
          "name": "manage-authorization",
          "description": "${role_manage-authorization}",
          "composite": false,
          "clientRole": true,
          "containerId": "6d24261c-a344-44a5-8d3e-aed7f8672294",
          "attributes": {}
        },
        {
          "id": "ad2d1774-ec67-4e5c-8d8b-2968399dd34e",
          "name": "view-users",
          "description": "${role_view-users}",
          "composite": true,
          "composites": {
            "client": {
              "realm-management": [
                "query-groups",
                "query-users"
              ]
            }
          },
          "clientRole": true,
          "containerId": "6d24261c-a344-44a5-8d3e-aed7f8672294",
          "attributes": {}
        },
        {
          "id": "e8c01213-2208-4df2-a298-4d2a74a55b48",
          "name": "query-groups",
          "description": "${role_query-groups}",
          "composite": false,
          "clientRole": true,
          "containerId": "6d24261c-a344-44a5-8d3e-aed7f8672294",
          "attributes": {}
        },
        {
          "id": "da3a8ced-5b1c-4f47-b420-e33597a8a743",
          "name": "view-events",
          "description": "${role_view-events}",
          "composite": false,
          "clientRole": true,
          "containerId": "6d24261c-a344-44a5-8d3e-aed7f8672294",
          "attributes": {}
        },
        {
          "id": "fa415123-16ef-4574-86f3-013c2ea9fa64",
          "name": "manage-clients",
          "description": "${role_manage-clients}",
          "composite": false,
          "clientRole": true,
          "containerId": "6d24261c-a344-44a5-8d3e-aed7f8672294",
          "attributes": {}
        },
        {
          "id": "61efae37-4f7d-4a94-9328-fc4a0c5a8ceb",
          "name": "realm-admin",
          "description": "${role_realm-admin}",
          "composite": true,
          "composites": {
            "client": {
              "realm-management": [
                "query-users",
                "manage-realm",
                "query-clients",
                "view-realm",
                "manage-events",
                "impersonation",
                "query-realms",
                "view-identity-providers",
                "manage-users",
                "view-clients",
                "create-client",
                "view-users",
                "manage-authorization",
                "query-groups",
                "view-events",
                "manage-clients",
                "view-authorization",
                "manage-identity-providers"
              ]
            }
          },
          "clientRole": true,
          "containerId": "6d24261c-a344-44a5-8d3e-aed7f8672294",
          "attributes": {}
        },
        {
          "id": "39f691e2-8648-42bc-b808-9ed1dd5cade1",
          "name": "view-authorization",
          "description": "${role_view-authorization}",
          "composite": false,
          "clientRole": true,
          "containerId": "6d24261c-a344-44a5-8d3e-aed7f8672294",
          "attributes": {}
        },
        {
          "id": "291199e7-266e-49fa-8b53-f257306e6326",
          "name": "manage-identity-providers",
          "description": "${role_manage-identity-providers}",
          "composite": false,
          "clientRole": true,
          "containerId": "6d24261c-a344-44a5-8d3e-aed7f8672294",
          "attributes": {}
        }
      ],
      "payment_service": [],
      "main_module_m2m": [],
      "security-admin-console": [],
      "admin-cli": [],
      "account-console": [],
      "broker": [
        {
          "id": "8276d82b-301f-4ef5-ac22-96996a12cab5",
          "name": "read-token",
          "description": "${role_read-token}",
          "composite": false,
          "clientRole": true,
          "containerId": "3feca41f-674d-4280-b07e-0ea420d3ebd7",
          "attributes": {}
        }
      ],
      "account": [
        {
          "id": "9b754e0a-5d10-46c8-90f2-b2eab89444ab",
          "name": "manage-account",
          "description": "${role_manage-account}",
          "composite": true,
          "composites": {
            "client": {
              "account": [
                "manage-account-links"
              ]
            }
          },
          "clientRole": true,
          "containerId": "620b6747-7529-4ced-b347-4eee3daa2af7",
          "attributes": {}
        },
        {
          "id": "871e3037-1888-4e5e-8c74-c6a2877ce7f8",
          "name": "view-applications",
          "description": "${role_view-applications}",
          "composite": false,
          "clientRole": true,
          "containerId": "620b6747-7529-4ced-b347-4eee3daa2af7",
          "attributes": {}
        },
        {
          "id": "ed045bd9-b89d-4eb4-b805-795d8516dde6",
          "name": "view-profile",
          "description": "${role_view-profile}",
          "composite": false,
          "clientRole": true,
          "containerId": "620b6747-7529-4ced-b347-4eee3daa2af7",
          "attributes": {}
        },
        {
          "id": "ef61c8ee-4c1b-4cba-90bf-c506d2e0b8a4",
          "name": "manage-consent",
          "description": "${role_manage-consent}",
          "composite": true,
          "composites": {
            "client": {
              "account": [
                "view-consent"
              ]
            }
          },
          "clientRole": true,
          "containerId": "620b6747-7529-4ced-b347-4eee3daa2af7",
          "attributes": {}
        },
        {
          "id": "86e33f75-0e37-4a79-892f-40d6d1320814",
          "name": "delete-account",
          "description": "${role_delete-account}",
          "composite": false,
          "clientRole": true,
          "containerId": "620b6747-7529-4ced-b347-4eee3daa2af7",
          "attributes": {}
        },
        {
          "id": "6ed21e0f-81d6-4922-bbc3-a72ca055038a",
          "name": "view-consent",
          "description": "${role_view-consent}",
          "composite": false,
          "clientRole": true,
          "containerId": "620b6747-7529-4ced-b347-4eee3daa2af7",
          "attributes": {}
        },
        {
          "id": "2dc2a21c-638d-4e1f-86be-92934eeb92fe",
          "name": "manage-account-links",
          "description": "${role_manage-account-links}",
          "composite": false,
          "clientRole": true,
          "containerId": "620b6747-7529-4ced-b347-4eee3daa2af7",
          "attributes": {}
        },
        {
          "id": "25d2b9ea-11ae-4e18-a848-ccb4173583f0",
          "name": "view-groups",
          "description": "${role_view-groups}",
          "composite": false,
          "clientRole": true,
          "containerId": "620b6747-7529-4ced-b347-4eee3daa2af7",
          "attributes": {}
        }
      ]
    }
  },
  "groups": [],
  "defaultRole": {
    "id": "66b8fbe6-f182-492e-8226-2e4821048fbe",
    "name": "default-roles-internet-shop",
    "description": "${role_default-roles}",
    "composite": true,
    "clientRole": false,
    "containerId": "f049e7c0-47ee-4913-b59c-b8db0693b8a3"
  },
  "requiredCredentials": [
    "password"
  ],
  "otpPolicyType": "totp",
  "otpPolicyAlgorithm": "HmacSHA1",
  "otpPolicyInitialCounter": 0,
  "otpPolicyDigits": 6,
  "otpPolicyLookAheadWindow": 1,
  "otpPolicyPeriod": 30,
  "otpPolicyCodeReusable": false,
  "otpSupportedApplications": [
    "totpAppFreeOTPName",
    "totpAppGoogleName",
    "totpAppMicrosoftAuthenticatorName"
  ],
  "localizationTexts": {},
  "webAuthnPolicyRpEntityName": "keycloak",
  "webAuthnPolicySignatureAlgorithms": [
    "ES256",
    "RS256"
  ],
  "webAuthnPolicyRpId": "",
  "webAuthnPolicyAttestationConveyancePreference": "not specified",
  "webAuthnPolicyAuthenticatorAttachment": "not specified",
  "webAuthnPolicyRequireResidentKey": "not specified",
  "webAuthnPolicyUserVerificationRequirement": "not specified",
  "webAuthnPolicyCreateTimeout": 0,
  "webAuthnPolicyAvoidSameAuthenticatorRegister": false,
  "webAuthnPolicyAcceptableAaguids": [],
  "webAuthnPolicyExtraOrigins": [],
  "webAuthnPolicyPasswordlessRpEntityName": "keycloak",
  "webAuthnPolicyPasswordlessSignatureAlgorithms": [
    "ES256",
    "RS256"
  ],
  "webAuthnPolicyPasswordlessRpId": "",
  "webAuthnPolicyPasswordlessAttestationConveyancePreference": "not specified",
  "webAuthnPolicyPasswordlessAuthenticatorAttachment": "not specified",
  "webAuthnPolicyPasswordlessRequireResidentKey": "not specified",
  "webAuthnPolicyPasswordlessUserVerificationRequirement": "not specified",
  "webAuthnPolicyPasswordlessCreateTimeout": 0,
  "webAuthnPolicyPasswordlessAvoidSameAuthenticatorRegister": false,
  "webAuthnPolicyPasswordlessAcceptableAaguids": [],
  "webAuthnPolicyPasswordlessExtraOrigins": [],
  "users": [
    {
      "id": "3c126e2e-35e0-4c3c-b057-3a4b40589c3c",
      "username": "service-account-main_module_m2m",
      "emailVerified": false,
      "createdTimestamp": 1744491100947,
      "enabled": true,
      "totp": false,
      "serviceAccountClientId": "main_module_m2m",
      "disableableCredentialTypes": [],
      "requiredActions": [],
      "realmRoles": [
        "default-roles-internet-shop"
      ],
      "notBefore": 0,
      "groups": []
    },
    {
      "username": "Adminuser",
      "enabled": true,
      "emailVerified": true,
      "firstName": "Admin",
      "lastName": "User",
      "email": "adminuser@example.com",
      "credentials": [
        {
          "type": "password",
          "value": "Adminpassword",
          "temporary": false
        }
      ],
      "realmRoles": [
        "default-roles-internet-shop",
        "USER",
        "ADMIN"
      ]
    },
    {
      "username": "testuser1",
      "enabled": true,
      "emailVerified": true,
      "firstName": "Test",
      "lastName": "User1",
      "email": "testuser1@example.com",
      "credentials": [
        {
          "type": "password",
          "value": "testpassword1",
          "temporary": false
        }
      ],
      "realmRoles": [
        "default-roles-internet-shop",
        "USER"
      ]
    },
    {
      "username": "testuser2",
      "enabled": true,
      "emailVerified": true,
      "firstName": "Test",
      "lastName": "User2",
      "email": "testuser2@example.com",
      "credentials": [
        {
          "type": "password",
          "value": "testpassword2",
          "temporary": false
        }
      ],
      "realmRoles": [
        "default-roles-internet-shop",
        "USER"
      ]
    }
  ],
  "scopeMappings": [
    {
      "clientScope": "offline_access",
      "roles": [
        "offline_access"
      ]
    }
  ],
  "clientScopeMappings": {
    "account": [
      {
        "client": "account-console",
        "roles": [
          "manage-account",
          "view-groups"
        ]
      }
    ]
  },
  "clients": [
    {
      "id": "620b6747-7529-4ced-b347-4eee3daa2af7",
      "clientId": "account",
      "name": "${client_account}",
      "rootUrl": "${authBaseUrl}",
      "baseUrl": "/realms/internet-shop/account/",
      "surrogateAuthRequired": false,
      "enabled": true,
      "alwaysDisplayInConsole": false,
      "clientAuthenticatorType": "client-secret",
      "redirectUris": [
        "/realms/internet-shop/account/*"
      ],
      "webOrigins": [],
      "notBefore": 0,
      "bearerOnly": false,
      "consentRequired": false,
      "standardFlowEnabled": true,
      "implicitFlowEnabled": false,
      "directAccessGrantsEnabled": false,
      "serviceAccountsEnabled": false,
      "publicClient": true,
      "frontchannelLogout": false,
      "protocol": "openid-connect",
      "attributes": {
        "realm_client": "false",
        "post.logout.redirect.uris": "+"
      },
      "authenticationFlowBindingOverrides": {},
      "fullScopeAllowed": false,
      "nodeReRegistrationTimeout": 0,
      "defaultClientScopes": [
        "web-origins",
        "acr",
        "roles",
        "profile",
        "basic",
        "email"
      ],
      "optionalClientScopes": [
        "address",
        "phone",
        "organization",
        "offline_access",
        "microprofile-jwt"
      ]
    },
    {
      "id": "a8ee09a0-01f0-4ac2-b7ee-e7c22ddf4d49",
      "clientId": "account-console",
      "name": "${client_account-console}",
      "rootUrl": "${authBaseUrl}",
      "baseUrl": "/realms/internet-shop/account/",
      "surrogateAuthRequired": false,
      "enabled": true,
      "alwaysDisplayInConsole": false,
      "clientAuthenticatorType": "client-secret",
      "redirectUris": [
        "/realms/internet-shop/account/*"
      ],
      "webOrigins": [],
      "notBefore": 0,
      "bearerOnly": false,
      "consentRequired": false,
      "standardFlowEnabled": true,
      "implicitFlowEnabled": false,
      "directAccessGrantsEnabled": false,
      "serviceAccountsEnabled": false,
      "publicClient": true,
      "frontchannelLogout": false,
      "protocol": "openid-connect",
      "attributes": {
        "realm_client": "false",
        "post.logout.redirect.uris": "+",
        "pkce.code.challenge.method": "S256"
      },
      "authenticationFlowBindingOverrides": {},
      "fullScopeAllowed": false,
      "nodeReRegistrationTimeout": 0,
      "protocolMappers": [
        {
          "id": "400d6bd2-60dc-4c30-b0e9-238884be444e",
          "name": "audience resolve",
          "protocol": "openid-connect",
          "protocolMapper": "oidc-audience-resolve-mapper",
          "consentRequired": false,
          "config": {}
        }
      ],
      "defaultClientScopes": [
        "web-origins",
        "acr",
        "roles",
        "profile",
        "basic",
        "email"
      ],
      "optionalClientScopes": [
        "address",
        "phone",
        "organization",
        "offline_access",
        "microprofile-jwt"
      ]
    },
    {
      "id": "4fc1e743-dfca-4fea-ae66-0857e489e547",
      "clientId": "admin-cli",
      "name": "${client_admin-cli}",
      "surrogateAuthRequired": false,
      "enabled": true,
      "alwaysDisplayInConsole": false,
      "clientAuthenticatorType": "client-secret",
      "redirectUris": [],
      "webOrigins": [],
      "notBefore": 0,
      "bearerOnly": false,
      "consentRequired": false,
      "standardFlowEnabled": false,
      "implicitFlowEnabled": false,
      "directAccessGrantsEnabled": true,
      "serviceAccountsEnabled": false,
      "publicClient": true,
      "frontchannelLogout": false,
      "protocol": "openid-connect",
      "attributes": {
        "realm_client": "false",
        "client.use.lightweight.access.token.enabled": "true",
        "post.logout.redirect.uris": "+"
      },
      "authenticationFlowBindingOverrides": {},
      "fullScopeAllowed": true,
      "nodeReRegistrationTimeout": 0,
      "defaultClientScopes": [
        "web-origins",
        "acr",
        "roles",
        "profile",
        "basic",
        "email"
      ],
      "optionalClientScopes": [
        "address",
        "phone",
        "organization",
        "offline_access",
        "microprofile-jwt"
      ]
    },
    {
      "id": "3feca41f-674d-4280-b07e-0ea420d3ebd7",
      "clientId": "broker",
      "name": "${client_broker}",
      "surrogateAuthRequired": false,
      "enabled": true,
      "alwaysDisplayInConsole": false,
      "clientAuthenticatorType": "client-secret",
      "redirectUris": [],
      "webOrigins": [],
      "notBefore": 0,
      "bearerOnly": true,
      "consentRequired": false,
      "standardFlowEnabled": true,
      "implicitFlowEnabled": false,
      "directAccessGrantsEnabled": false,
      "serviceAccountsEnabled": false,
      "publicClient": false,
      "frontchannelLogout": false,
      "protocol": "openid-connect",
      "attributes": {
        "realm_client": "true",
        "post.logout.redirect.uris": "+"
      },
      "authenticationFlowBindingOverrides": {},
      "fullScopeAllowed": false,
      "nodeReRegistrationTimeout": 0,
      "defaultClientScopes": [
        "web-origins",
        "acr",
        "roles",
        "profile",
        "basic",
        "email"
      ],
      "optionalClientScopes": [
        "address",
        "phone",
        "organization",
        "offline_access",
        "microprofile-jwt"
      ]
    },
    {
      "id": "586f99f9-41b7-4757-bb4b-ab6dd0568200",
      "clientId": "main_module",
      "name": "Main Module",
      "description": "Main module of internet-shop project (Authorization code flow)",
      "rootUrl": "http://localhost:8082",
      "adminUrl": "http://localhost:8082",
      "baseUrl": "",
      "surrogateAuthRequired": false,
      "enabled": true,
      "alwaysDisplayInConsole": false,
      "clientAuthenticatorType": "client-secret",
      "secret": "KFEgqu1CIlMNc2EsLhupNHSIsjwMefpA",
      "redirectUris": [
        "http://localhost:8082/*"
      ],
      "webOrigins": [
        "http://localhost:8082/*"
      ],
      "notBefore": 0,
      "bearerOnly": false,
      "consentRequired": false,
      "standardFlowEnabled": true,
      "implicitFlowEnabled": true,
      "directAccessGrantsEnabled": true,
      "serviceAccountsEnabled": false,
      "publicClient": false,
      "frontchannelLogout": true,
      "protocol": "openid-connect",
      "attributes": {
        "realm_client": "false",
        "oidc.ciba.grant.enabled": "false",
        "client.secret.creation.time": "1744485560",
        "backchannel.logout.session.required": "true",
        "post.logout.redirect.uris": "http://localhost:8082/*",
        "frontchannel.logout.session.required": "true",
        "oauth2.device.authorization.grant.enabled": "false",
        "display.on.consent.screen": "false",
        "use.jwks.url": "false",
        "backchannel.logout.revoke.offline.tokens": "false"
      },
      "authenticationFlowBindingOverrides": {},
      "fullScopeAllowed": true,
      "nodeReRegistrationTimeout": -1,
      "defaultClientScopes": [
        "web-origins",
        "acr",
        "roles",
        "profile",
        "basic",
        "email"
      ],
      "optionalClientScopes": [
        "address",
        "phone",
        "organization",
        "offline_access",
        "microprofile-jwt"
      ]
    },
    {
      "id": "3f5154bf-45e7-454a-9c13-b26e1af4fa1e",
      "clientId": "main_module_m2m",
      "name": "Main Module Client",
      "description": "Main module of internet-shop project as an m2m client (client credentials flow)",
      "rootUrl": "",
      "adminUrl": "",
      "baseUrl": "",
      "surrogateAuthRequired": false,
      "enabled": true,
      "alwaysDisplayInConsole": false,
      "clientAuthenticatorType": "client-secret",
      "secret": "FqMhe3sOQGdtsYDg9m8FPe9OFjSURjgj",
      "redirectUris": [
        "/*"
      ],
      "webOrigins": [
        "/*"
      ],
      "notBefore": 0,
      "bearerOnly": false,
      "consentRequired": false,
      "standardFlowEnabled": true,
      "implicitFlowEnabled": false,
      "directAccessGrantsEnabled": true,
      "serviceAccountsEnabled": true,
      "publicClient": false,
      "frontchannelLogout": true,
      "protocol": "openid-connect",
      "attributes": {
        "realm_client": "false",
        "oidc.ciba.grant.enabled": "false",
        "client.secret.creation.time": "1744491100",
        "backchannel.logout.session.required": "true",
        "post.logout.redirect.uris": "+",
        "oauth2.device.authorization.grant.enabled": "false",
        "backchannel.logout.revoke.offline.tokens": "false"
      },
      "authenticationFlowBindingOverrides": {},
      "fullScopeAllowed": true,
      "nodeReRegistrationTimeout": -1,
      "defaultClientScopes": [
        "service_account",
        "web-origins",
        "acr",
        "roles",
        "profile",
        "basic",
        "email"
      ],
      "optionalClientScopes": [
        "address",
        "phone",
        "organization",
        "offline_access",
        "microprofile-jwt"
      ]
    },
    {
      "id": "40b035b9-bba7-495e-be5a-d7b251bb7f12",
      "clientId": "payment_service",
      "name": "Payment Service",
      "description": "",
      "rootUrl": "",
      "adminUrl": "",
      "baseUrl": "",
      "surrogateAuthRequired": false,
      "enabled": true,
      "alwaysDisplayInConsole": false,
      "clientAuthenticatorType": "client-secret",
      "secret": "**********",
      "redirectUris": [
        "/*"
      ],
      "webOrigins": [
        "/*"
      ],
      "notBefore": 0,
      "bearerOnly": false,
      "consentRequired": false,
      "standardFlowEnabled": false,
      "implicitFlowEnabled": false,
      "directAccessGrantsEnabled": false,
      "serviceAccountsEnabled": false,
      "publicClient": false,
      "frontchannelLogout": true,
      "protocol": "openid-connect",
      "attributes": {
        "realm_client": "false",
        "oidc.ciba.grant.enabled": "false",
        "client.secret.creation.time": "1744660152",
        "backchannel.logout.session.required": "true",
        "frontchannel.logout.session.required": "true",
        "post.logout.redirect.uris": "+",
        "oauth2.device.authorization.grant.enabled": "false",
        "display.on.consent.screen": "false",
        "backchannel.logout.revoke.offline.tokens": "false"
      },
      "authenticationFlowBindingOverrides": {},
      "fullScopeAllowed": true,
      "nodeReRegistrationTimeout": -1,
      "defaultClientScopes": [
        "web-origins",
        "acr",
        "roles",
        "profile",
        "basic",
        "email"
      ],
      "optionalClientScopes": [
        "address",
        "phone",
        "organization",
        "offline_access",
        "microprofile-jwt"
      ]
    },
    {
      "id": "6d24261c-a344-44a5-8d3e-aed7f8672294",
      "clientId": "realm-management",
      "name": "${client_realm-management}",
      "surrogateAuthRequired": false,
      "enabled": true,
      "alwaysDisplayInConsole": false,
      "clientAuthenticatorType": "client-secret",
      "redirectUris": [],
      "webOrigins": [],
      "notBefore": 0,
      "bearerOnly": true,
      "consentRequired": false,
      "standardFlowEnabled": true,
      "implicitFlowEnabled": false,
      "directAccessGrantsEnabled": false,
      "serviceAccountsEnabled": false,
      "publicClient": false,
      "frontchannelLogout": false,
      "protocol": "openid-connect",
      "attributes": {
        "realm_client": "true",
        "post.logout.redirect.uris": "+"
      },
      "authenticationFlowBindingOverrides": {},
      "fullScopeAllowed": false,
      "nodeReRegistrationTimeout": 0,
      "defaultClientScopes": [
        "web-origins",
        "acr",
        "roles",
        "profile",
        "basic",
        "email"
      ],
      "optionalClientScopes": [
        "address",
        "phone",
        "organization",
        "offline_access",
        "microprofile-jwt"
      ]
    },
    {
      "id": "337300cb-d9f7-4928-89d7-2ed2b9660129",
      "clientId": "security-admin-console",
      "name": "${client_security-admin-console}",
      "rootUrl": "${authAdminUrl}",
      "baseUrl": "/admin/internet-shop/console/",
      "surrogateAuthRequired": false,
      "enabled": true,
      "alwaysDisplayInConsole": false,
      "clientAuthenticatorType": "client-secret",
      "redirectUris": [
        "/admin/internet-shop/console/*"
      ],
      "webOrigins": [
        "+"
      ],
      "notBefore": 0,
      "bearerOnly": false,
      "consentRequired": false,
      "standardFlowEnabled": true,
      "implicitFlowEnabled": false,
      "directAccessGrantsEnabled": false,
      "serviceAccountsEnabled": false,
      "publicClient": true,
      "frontchannelLogout": false,
      "protocol": "openid-connect",
      "attributes": {
        "realm_client": "false",
        "client.use.lightweight.access.token.enabled": "true",
        "post.logout.redirect.uris": "+",
        "pkce.code.challenge.method": "S256"
      },
      "authenticationFlowBindingOverrides": {},
      "fullScopeAllowed": true,
      "nodeReRegistrationTimeout": 0,
      "protocolMappers": [
        {
          "id": "00b57339-2305-44cf-8de1-3665328e9028",
          "name": "locale",
          "protocol": "openid-connect",
          "protocolMapper": "oidc-usermodel-attribute-mapper",
          "consentRequired": false,
          "config": {
            "introspection.token.claim": "true",
            "userinfo.token.claim": "true",
            "user.attribute": "locale",
            "id.token.claim": "true",
            "access.token.claim": "true",
            "claim.name": "locale",
            "jsonType.label": "String"
          }
        }
      ],
      "defaultClientScopes": [
        "web-origins",
        "acr",
        "roles",
        "profile",
        "basic",
        "email"
      ],
      "optionalClientScopes": [
        "address",
        "phone",
        "organization",
        "offline_access",
        "microprofile-jwt"
      ]
    }
  ],
  "clientScopes": [
    {
      "id": "842857a0-0832-4091-9e5b-e8e0119f5eb8",
      "name": "organization",
      "description": "Additional claims about the organization a subject belongs to",
      "protocol": "openid-connect",
      "attributes": {
        "include.in.token.scope": "true",
        "consent.screen.text": "${organizationScopeConsentText}",
        "display.on.consent.screen": "true"
      },
      "protocolMappers": [
        {
          "id": "a13b51d9-b620-4eee-b50b-f17a753bbb36",
          "name": "organization",
          "protocol": "openid-connect",
          "protocolMapper": "oidc-organization-membership-mapper",
          "consentRequired": false,
          "config": {
            "introspection.token.claim": "true",
            "multivalued": "true",
            "userinfo.token.claim": "true",
            "id.token.claim": "true",
            "access.token.claim": "true",
            "claim.name": "organization",
            "jsonType.label": "String"
          }
        }
      ]
    },
    {
      "id": "b3773008-3e06-43d2-93d8-1ee5aef2419f",
      "name": "roles",
      "description": "OpenID Connect scope for add user roles to the access token",
      "protocol": "openid-connect",
      "attributes": {
        "include.in.token.scope": "false",
        "consent.screen.text": "${rolesScopeConsentText}",
        "display.on.consent.screen": "true"
      },
      "protocolMappers": [
        {
          "id": "a8221fbd-c645-4ee0-814d-ae65651a3adf",
          "name": "client roles",
          "protocol": "openid-connect",
          "protocolMapper": "oidc-usermodel-client-role-mapper",
          "consentRequired": false,
          "config": {
            "user.attribute": "foo",
            "introspection.token.claim": "true",
            "access.token.claim": "true",
            "claim.name": "resource_access.${client_id}.roles",
            "jsonType.label": "String",
            "multivalued": "true"
          }
        },
        {
          "id": "9ef6b462-13c9-4ae3-8997-f400069c88cb",
          "name": "realm roles",
          "protocol": "openid-connect",
          "protocolMapper": "oidc-usermodel-realm-role-mapper",
          "consentRequired": false,
          "config": {
            "introspection.token.claim": "true",
            "multivalued": "true",
            "userinfo.token.claim": "false",
            "user.attribute": "foo",
            "id.token.claim": "true",
            "lightweight.claim": "false",
            "access.token.claim": "true",
            "claim.name": "realm_access.roles",
            "jsonType.label": "String"
          }
        },
        {
          "id": "4d47e008-d9d4-40a9-8396-534721cd8df3",
          "name": "audience resolve",
          "protocol": "openid-connect",
          "protocolMapper": "oidc-audience-resolve-mapper",
          "consentRequired": false,
          "config": {
            "introspection.token.claim": "true",
            "access.token.claim": "true"
          }
        }
      ]
    },
    {
      "id": "b970209a-e18b-4214-8709-cf19d8430f3a",
      "name": "profile",
      "description": "OpenID Connect built-in scope: profile",
      "protocol": "openid-connect",
      "attributes": {
        "include.in.token.scope": "true",
        "consent.screen.text": "${profileScopeConsentText}",
        "display.on.consent.screen": "true"
      },
      "protocolMappers": [
        {
          "id": "2896034e-5bc4-44ca-8006-8a876adb7f0f",
          "name": "picture",
          "protocol": "openid-connect",
          "protocolMapper": "oidc-usermodel-attribute-mapper",
          "consentRequired": false,
          "config": {
            "introspection.token.claim": "true",
            "userinfo.token.claim": "true",
            "user.attribute": "picture",
            "id.token.claim": "true",
            "access.token.claim": "true",
            "claim.name": "picture",
            "jsonType.label": "String"
          }
        },
        {
          "id": "614a6ce4-4b37-4d91-8ebf-551ffd21279d",
          "name": "full name",
          "protocol": "openid-connect",
          "protocolMapper": "oidc-full-name-mapper",
          "consentRequired": false,
          "config": {
            "id.token.claim": "true",
            "introspection.token.claim": "true",
            "access.token.claim": "true",
            "userinfo.token.claim": "true"
          }
        },
        {
          "id": "6cf7b537-0568-4589-a941-35a418f5a620",
          "name": "middle name",
          "protocol": "openid-connect",
          "protocolMapper": "oidc-usermodel-attribute-mapper",
          "consentRequired": false,
          "config": {
            "introspection.token.claim": "true",
            "userinfo.token.claim": "true",
            "user.attribute": "middleName",
            "id.token.claim": "true",
            "access.token.claim": "true",
            "claim.name": "middle_name",
            "jsonType.label": "String"
          }
        },
        {
          "id": "e9ae4e3e-8a41-401a-bcc7-ceeaa72fd420",
          "name": "username",
          "protocol": "openid-connect",
          "protocolMapper": "oidc-usermodel-attribute-mapper",
          "consentRequired": false,
          "config": {
            "introspection.token.claim": "true",
            "userinfo.token.claim": "true",
            "user.attribute": "username",
            "id.token.claim": "true",
            "access.token.claim": "true",
            "claim.name": "preferred_username",
            "jsonType.label": "String"
          }
        },
        {
          "id": "f7b2f1e6-818c-4379-afef-222aeaf2bede",
          "name": "updated at",
          "protocol": "openid-connect",
          "protocolMapper": "oidc-usermodel-attribute-mapper",
          "consentRequired": false,
          "config": {
            "introspection.token.claim": "true",
            "userinfo.token.claim": "true",
            "user.attribute": "updatedAt",
            "id.token.claim": "true",
            "access.token.claim": "true",
            "claim.name": "updated_at",
            "jsonType.label": "long"
          }
        },
        {
          "id": "c1d058b6-4c46-49ad-a19c-d18c419b996f",
          "name": "nickname",
          "protocol": "openid-connect",
          "protocolMapper": "oidc-usermodel-attribute-mapper",
          "consentRequired": false,
          "config": {
            "introspection.token.claim": "true",
            "userinfo.token.claim": "true",
            "user.attribute": "nickname",
            "id.token.claim": "true",
            "access.token.claim": "true",
            "claim.name": "nickname",
            "jsonType.label": "String"
          }
        },
        {
          "id": "1e1ffcc2-4e1d-44a9-bfe2-d20200c1bcd7",
          "name": "gender",
          "protocol": "openid-connect",
          "protocolMapper": "oidc-usermodel-attribute-mapper",
          "consentRequired": false,
          "config": {
            "introspection.token.claim": "true",
            "userinfo.token.claim": "true",
            "user.attribute": "gender",
            "id.token.claim": "true",
            "access.token.claim": "true",
            "claim.name": "gender",
            "jsonType.label": "String"
          }
        },
        {
          "id": "4a079e5e-1ba9-4076-8cc6-dcebd00914f7",
          "name": "zoneinfo",
          "protocol": "openid-connect",
          "protocolMapper": "oidc-usermodel-attribute-mapper",
          "consentRequired": false,
          "config": {
            "introspection.token.claim": "true",
            "userinfo.token.claim": "true",
            "user.attribute": "zoneinfo",
            "id.token.claim": "true",
            "access.token.claim": "true",
            "claim.name": "zoneinfo",
            "jsonType.label": "String"
          }
        },
        {
          "id": "81527697-b86d-42f6-b345-da80136db32d",
          "name": "family name",
          "protocol": "openid-connect",
          "protocolMapper": "oidc-usermodel-attribute-mapper",
          "consentRequired": false,
          "config": {
            "introspection.token.claim": "true",
            "userinfo.token.claim": "true",
            "user.attribute": "lastName",
            "id.token.claim": "true",
            "access.token.claim": "true",
            "claim.name": "family_name",
            "jsonType.label": "String"
          }
        },
        {
          "id": "53f57d46-9a19-4d77-9fd2-dd59cc624807",
          "name": "given name",
          "protocol": "openid-connect",
          "protocolMapper": "oidc-usermodel-attribute-mapper",
          "consentRequired": false,
          "config": {
            "introspection.token.claim": "true",
            "userinfo.token.claim": "true",
            "user.attribute": "firstName",
            "id.token.claim": "true",
            "access.token.claim": "true",
            "claim.name": "given_name",
            "jsonType.label": "String"
          }
        },
        {
          "id": "a39b6d25-f5bf-4346-b85b-e48373fc2c6b",
          "name": "birthdate",
          "protocol": "openid-connect",
          "protocolMapper": "oidc-usermodel-attribute-mapper",
          "consentRequired": false,
          "config": {
            "introspection.token.claim": "true",
            "userinfo.token.claim": "true",
            "user.attribute": "birthdate",
            "id.token.claim": "true",
            "access.token.claim": "true",
            "claim.name": "birthdate",
            "jsonType.label": "String"
          }
        },
        {
          "id": "4389ce62-54dc-4ace-9591-dbc16fdcb490",
          "name": "locale",
          "protocol": "openid-connect",
          "protocolMapper": "oidc-usermodel-attribute-mapper",
          "consentRequired": false,
          "config": {
            "introspection.token.claim": "true",
            "userinfo.token.claim": "true",
            "user.attribute": "locale",
            "id.token.claim": "true",
            "access.token.claim": "true",
            "claim.name": "locale",
            "jsonType.label": "String"
          }
        },
        {
          "id": "7e73ef54-95fc-4c18-b108-4712049ffcd4",
          "name": "profile",
          "protocol": "openid-connect",
          "protocolMapper": "oidc-usermodel-attribute-mapper",
          "consentRequired": false,
          "config": {
            "introspection.token.claim": "true",
            "userinfo.token.claim": "true",
            "user.attribute": "profile",
            "id.token.claim": "true",
            "access.token.claim": "true",
            "claim.name": "profile",
            "jsonType.label": "String"
          }
        },
        {
          "id": "2d06375c-6234-4b11-97e6-5aad74131b20",
          "name": "website",
          "protocol": "openid-connect",
          "protocolMapper": "oidc-usermodel-attribute-mapper",
          "consentRequired": false,
          "config": {
            "introspection.token.claim": "true",
            "userinfo.token.claim": "true",
            "user.attribute": "website",
            "id.token.claim": "true",
            "access.token.claim": "true",
            "claim.name": "website",
            "jsonType.label": "String"
          }
        }
      ]
    },
    {
      "id": "bde5d68f-8f4d-44ec-8313-ced8f490c267",
      "name": "microprofile-jwt",
      "description": "Microprofile - JWT built-in scope",
      "protocol": "openid-connect",
      "attributes": {
        "include.in.token.scope": "true",
        "display.on.consent.screen": "false"
      },
      "protocolMappers": [
        {
          "id": "72b78037-4f45-4bc5-a7fc-2a2ed4fc4c38",
          "name": "groups",
          "protocol": "openid-connect",
          "protocolMapper": "oidc-usermodel-realm-role-mapper",
          "consentRequired": false,
          "config": {
            "introspection.token.claim": "true",
            "multivalued": "true",
            "userinfo.token.claim": "true",
            "user.attribute": "foo",
            "id.token.claim": "true",
            "access.token.claim": "true",
            "claim.name": "groups",
            "jsonType.label": "String"
          }
        },
        {
          "id": "2d9aa0fb-9c7b-463f-9cb3-7976648f96a4",
          "name": "upn",
          "protocol": "openid-connect",
          "protocolMapper": "oidc-usermodel-attribute-mapper",
          "consentRequired": false,
          "config": {
            "introspection.token.claim": "true",
            "userinfo.token.claim": "true",
            "user.attribute": "username",
            "id.token.claim": "true",
            "access.token.claim": "true",
            "claim.name": "upn",
            "jsonType.label": "String"
          }
        }
      ]
    },
    {
      "id": "135f9b0f-00bf-46f9-a0ce-d314bf4c1cc0",
      "name": "basic",
      "description": "OpenID Connect scope for add all basic claims to the token",
      "protocol": "openid-connect",
      "attributes": {
        "include.in.token.scope": "false",
        "display.on.consent.screen": "false"
      },
      "protocolMappers": [
        {
          "id": "993b452a-77a3-454e-a403-d8ef12ad1920",
          "name": "auth_time",
          "protocol": "openid-connect",
          "protocolMapper": "oidc-usersessionmodel-note-mapper",
          "consentRequired": false,
          "config": {
            "user.session.note": "AUTH_TIME",
            "introspection.token.claim": "true",
            "userinfo.token.claim": "true",
            "id.token.claim": "true",
            "access.token.claim": "true",
            "claim.name": "auth_time",
            "jsonType.label": "long"
          }
        },
        {
          "id": "b1d5a71d-0754-4360-b1fc-9b9ed1260971",
          "name": "sub",
          "protocol": "openid-connect",
          "protocolMapper": "oidc-sub-mapper",
          "consentRequired": false,
          "config": {
            "introspection.token.claim": "true",
            "access.token.claim": "true"
          }
        }
      ]
    },
    {
      "id": "697348fc-8e9f-416b-92fd-cdb76b84b9c9",
      "name": "phone",
      "description": "OpenID Connect built-in scope: phone",
      "protocol": "openid-connect",
      "attributes": {
        "include.in.token.scope": "true",
        "consent.screen.text": "${phoneScopeConsentText}",
        "display.on.consent.screen": "true"
      },
      "protocolMappers": [
        {
          "id": "b1d10258-14b1-4357-9f07-3c79c657a25b",
          "name": "phone number",
          "protocol": "openid-connect",
          "protocolMapper": "oidc-usermodel-attribute-mapper",
          "consentRequired": false,
          "config": {
            "introspection.token.claim": "true",
            "userinfo.token.claim": "true",
            "user.attribute": "phoneNumber",
            "id.token.claim": "true",
            "access.token.claim": "true",
            "claim.name": "phone_number",
            "jsonType.label": "String"
          }
        },
        {
          "id": "ccd57205-306d-423d-b97b-fb8597b765d3",
          "name": "phone number verified",
          "protocol": "openid-connect",
          "protocolMapper": "oidc-usermodel-attribute-mapper",
          "consentRequired": false,
          "config": {
            "introspection.token.claim": "true",
            "userinfo.token.claim": "true",
            "user.attribute": "phoneNumberVerified",
            "id.token.claim": "true",
            "access.token.claim": "true",
            "claim.name": "phone_number_verified",
            "jsonType.label": "boolean"
          }
        }
      ]
    },
    {
      "id": "88bd259d-9a6d-4f7c-a77b-418a3170431e",
      "name": "address",
      "description": "OpenID Connect built-in scope: address",
      "protocol": "openid-connect",
      "attributes": {
        "include.in.token.scope": "true",
        "consent.screen.text": "${addressScopeConsentText}",
        "display.on.consent.screen": "true"
      },
      "protocolMappers": [
        {
          "id": "4fc9314f-e2bf-499d-b78d-6236f45891da",
          "name": "address",
          "protocol": "openid-connect",
          "protocolMapper": "oidc-address-mapper",
          "consentRequired": false,
          "config": {
            "user.attribute.formatted": "formatted",
            "user.attribute.country": "country",
            "introspection.token.claim": "true",
            "user.attribute.postal_code": "postal_code",
            "userinfo.token.claim": "true",
            "user.attribute.street": "street",
            "id.token.claim": "true",
            "user.attribute.region": "region",
            "access.token.claim": "true",
            "user.attribute.locality": "locality"
          }
        }
      ]
    },
    {
      "id": "2adcbfc7-93ae-4ff7-a19b-fa94c08bf5c5",
      "name": "acr",
      "description": "OpenID Connect scope for add acr (authentication context class reference) to the token",
      "protocol": "openid-connect",
      "attributes": {
        "include.in.token.scope": "false",
        "display.on.consent.screen": "false"
      },
      "protocolMappers": [
        {
          "id": "dc91091b-8f30-45d8-a69f-0bdb71a5b038",
          "name": "acr loa level",
          "protocol": "openid-connect",
          "protocolMapper": "oidc-acr-mapper",
          "consentRequired": false,
          "config": {
            "id.token.claim": "true",
            "introspection.token.claim": "true",
            "access.token.claim": "true",
            "userinfo.token.claim": "true"
          }
        }
      ]
    },
    {
      "id": "eb94da8a-9d17-4748-89f3-04fae45e11f5",
      "name": "role_list",
      "description": "SAML role list",
      "protocol": "saml",
      "attributes": {
        "consent.screen.text": "${samlRoleListScopeConsentText}",
        "display.on.consent.screen": "true"
      },
      "protocolMappers": [
        {
          "id": "b2a7d5d7-042c-48fd-b459-434a26ba6ead",
          "name": "role list",
          "protocol": "saml",
          "protocolMapper": "saml-role-list-mapper",
          "consentRequired": false,
          "config": {
            "single": "false",
            "attribute.nameformat": "Basic",
            "attribute.name": "Role"
          }
        }
      ]
    },
    {
      "id": "e5d4ad22-9366-4f76-94a1-dec540638d60",
      "name": "service_account",
      "description": "Specific scope for a client enabled for service accounts",
      "protocol": "openid-connect",
      "attributes": {
        "include.in.token.scope": "false",
        "display.on.consent.screen": "false"
      },
      "protocolMappers": [
        {
          "id": "52d97ac8-b3fc-4356-89dc-91f647edbb90",
          "name": "Client Host",
          "protocol": "openid-connect",
          "protocolMapper": "oidc-usersessionmodel-note-mapper",
          "consentRequired": false,
          "config": {
            "user.session.note": "clientHost",
            "introspection.token.claim": "true",
            "userinfo.token.claim": "true",
            "id.token.claim": "true",
            "access.token.claim": "true",
            "claim.name": "clientHost",
            "jsonType.label": "String"
          }
        },
        {
          "id": "b93ba2be-e379-4d27-96c7-6a7a69219ff5",
          "name": "Client IP Address",
          "protocol": "openid-connect",
          "protocolMapper": "oidc-usersessionmodel-note-mapper",
          "consentRequired": false,
          "config": {
            "user.session.note": "clientAddress",
            "introspection.token.claim": "true",
            "userinfo.token.claim": "true",
            "id.token.claim": "true",
            "access.token.claim": "true",
            "claim.name": "clientAddress",
            "jsonType.label": "String"
          }
        },
        {
          "id": "582a6b61-c642-479a-8ab0-b7ee087f9f61",
          "name": "Client ID",
          "protocol": "openid-connect",
          "protocolMapper": "oidc-usersessionmodel-note-mapper",
          "consentRequired": false,
          "config": {
            "user.session.note": "client_id",
            "introspection.token.claim": "true",
            "userinfo.token.claim": "true",
            "id.token.claim": "true",
            "access.token.claim": "true",
            "claim.name": "client_id",
            "jsonType.label": "String"
          }
        }
      ]
    },
    {
      "id": "06f417ae-5119-4483-8998-1dabfd3c56ad",
      "name": "offline_access",
      "description": "OpenID Connect built-in scope: offline_access",
      "protocol": "openid-connect",
      "attributes": {
        "consent.screen.text": "${offlineAccessScopeConsentText}",
        "display.on.consent.screen": "true"
      }
    },
    {
      "id": "fadebfa6-096c-4c67-89e3-e42b41982642",
      "name": "email",
      "description": "OpenID Connect built-in scope: email",
      "protocol": "openid-connect",
      "attributes": {
        "include.in.token.scope": "true",
        "consent.screen.text": "${emailScopeConsentText}",
        "display.on.consent.screen": "true"
      },
      "protocolMappers": [
        {
          "id": "8b8a8128-c479-4b30-a387-9c4f6f383fd7",
          "name": "email verified",
          "protocol": "openid-connect",
          "protocolMapper": "oidc-usermodel-property-mapper",
          "consentRequired": false,
          "config": {
            "introspection.token.claim": "true",
            "userinfo.token.claim": "true",
            "user.attribute": "emailVerified",
            "id.token.claim": "true",
            "access.token.claim": "true",
            "claim.name": "email_verified",
            "jsonType.label": "boolean"
          }
        },
        {
          "id": "5300a005-d60e-49fd-a879-850bdc03fb60",
          "name": "email",
          "protocol": "openid-connect",
          "protocolMapper": "oidc-usermodel-attribute-mapper",
          "consentRequired": false,
          "config": {
            "introspection.token.claim": "true",
            "userinfo.token.claim": "true",
            "user.attribute": "email",
            "id.token.claim": "true",
            "access.token.claim": "true",
            "claim.name": "email",
            "jsonType.label": "String"
          }
        }
      ]
    },
    {
      "id": "3176f15f-12a0-45a5-9a72-44a0ca86a3cb",
      "name": "saml_organization",
      "description": "Organization Membership",
      "protocol": "saml",
      "attributes": {
        "display.on.consent.screen": "false"
      },
      "protocolMappers": [
        {
          "id": "9fab9450-1304-4954-a464-6406d9c59692",
          "name": "organization",
          "protocol": "saml",
          "protocolMapper": "saml-organization-membership-mapper",
          "consentRequired": false,
          "config": {}
        }
      ]
    },
    {
      "id": "4f80c38b-d0af-4a3b-95a0-11f1e9638dfb",
      "name": "web-origins",
      "description": "OpenID Connect scope for add allowed web origins to the access token",
      "protocol": "openid-connect",
      "attributes": {
        "include.in.token.scope": "false",
        "consent.screen.text": "",
        "display.on.consent.screen": "false"
      },
      "protocolMappers": [
        {
          "id": "c2098a2d-5d16-4c3e-90c1-c1536ae152fc",
          "name": "allowed web origins",
          "protocol": "openid-connect",
          "protocolMapper": "oidc-allowed-origins-mapper",
          "consentRequired": false,
          "config": {
            "introspection.token.claim": "true",
            "access.token.claim": "true"
          }
        }
      ]
    }
  ],
  "defaultDefaultClientScopes": [
    "role_list",
    "saml_organization",
    "profile",
    "email",
    "roles",
    "web-origins",
    "acr",
    "basic"
  ],
  "defaultOptionalClientScopes": [
    "offline_access",
    "address",
    "phone",
    "microprofile-jwt",
    "organization"
  ],
  "browserSecurityHeaders": {
    "contentSecurityPolicyReportOnly": "",
    "xContentTypeOptions": "nosniff",
    "referrerPolicy": "no-referrer",
    "xRobotsTag": "none",
    "xFrameOptions": "SAMEORIGIN",
    "contentSecurityPolicy": "frame-src 'self'; frame-ancestors 'self'; object-src 'none';",
    "xXSSProtection": "1; mode=block",
    "strictTransportSecurity": "max-age=31536000; includeSubDomains"
  },
  "smtpServer": {},
  "eventsEnabled": false,
  "eventsListeners": [
    "jboss-logging"
  ],
  "enabledEventTypes": [],
  "adminEventsEnabled": false,
  "adminEventsDetailsEnabled": false,
  "identityProviders": [],
  "identityProviderMappers": [],
  "components": {
    "org.keycloak.services.clientregistration.policy.ClientRegistrationPolicy": [
      {
        "id": "8da1541a-6abc-4098-b9a4-e83fa269f001",
        "name": "Full Scope Disabled",
        "providerId": "scope",
        "subType": "anonymous",
        "subComponents": {},
        "config": {}
      },
      {
        "id": "cde3adbd-414b-4e74-8f80-991ce0ef9937",
        "name": "Allowed Client Scopes",
        "providerId": "allowed-client-templates",
        "subType": "authenticated",
        "subComponents": {},
        "config": {
          "allow-default-scopes": [
            "true"
          ]
        }
      },
      {
        "id": "b0079e65-ba4b-4c32-96f5-b63d5f4c48dc",
        "name": "Allowed Protocol Mapper Types",
        "providerId": "allowed-protocol-mappers",
        "subType": "anonymous",
        "subComponents": {},
        "config": {
          "allowed-protocol-mapper-types": [
            "oidc-address-mapper",
            "oidc-sha256-pairwise-sub-mapper",
            "saml-role-list-mapper",
            "saml-user-attribute-mapper",
            "oidc-usermodel-property-mapper",
            "oidc-full-name-mapper",
            "oidc-usermodel-attribute-mapper",
            "saml-user-property-mapper"
          ]
        }
      },
      {
        "id": "5214fa66-fc75-48e4-8a96-94ac8c0e7bd2",
        "name": "Consent Required",
        "providerId": "consent-required",
        "subType": "anonymous",
        "subComponents": {},
        "config": {}
      },
      {
        "id": "3ef7d037-f140-40ca-bba1-b72c47dc6777",
        "name": "Max Clients Limit",
        "providerId": "max-clients",
        "subType": "anonymous",
        "subComponents": {},
        "config": {
          "max-clients": [
            "200"
          ]
        }
      },
      {
        "id": "227792ec-3db5-4ccd-8366-7145c36c00ca",
        "name": "Allowed Protocol Mapper Types",
        "providerId": "allowed-protocol-mappers",
        "subType": "authenticated",
        "subComponents": {},
        "config": {
          "allowed-protocol-mapper-types": [
            "saml-role-list-mapper",
            "saml-user-attribute-mapper",
            "oidc-usermodel-property-mapper",
            "oidc-usermodel-attribute-mapper",
            "oidc-full-name-mapper",
            "oidc-sha256-pairwise-sub-mapper",
            "oidc-address-mapper",
            "saml-user-property-mapper"
          ]
        }
      },
      {
        "id": "65cb52d1-e7fc-4cee-82d6-ace2fa6478a1",
        "name": "Trusted Hosts",
        "providerId": "trusted-hosts",
        "subType": "anonymous",
        "subComponents": {},
        "config": {
          "host-sending-registration-request-must-match": [
            "true"
          ],
          "client-uris-must-match": [
            "true"
          ]
        }
      },
      {
        "id": "43edcf93-4b30-44dc-b673-3f774c245318",
        "name": "Allowed Client Scopes",
        "providerId": "allowed-client-templates",
        "subType": "anonymous",
        "subComponents": {},
        "config": {
          "allow-default-scopes": [
            "true"
          ]
        }
      }
    ],
    "org.keycloak.keys.KeyProvider": [
      {
        "id": "52ec7264-b3dd-4fc7-8b8a-19656b2fb31b",
        "name": "hmac-generated-hs512",
        "providerId": "hmac-generated",
        "subComponents": {},
        "config": {
          "priority": [
            "100"
          ],
          "algorithm": [
            "HS512"
          ]
        }
      },
      {
        "id": "18124015-c8ce-418b-b47f-7c2575071e9f",
        "name": "rsa-enc-generated",
        "providerId": "rsa-enc-generated",
        "subComponents": {},
        "config": {
          "priority": [
            "100"
          ],
          "algorithm": [
            "RSA-OAEP"
          ]
        }
      },
      {
        "id": "6ce1c25a-1018-40db-8055-1e5a0dcf77a7",
        "name": "rsa-generated",
        "providerId": "rsa-generated",
        "subComponents": {},
        "config": {
          "priority": [
            "100"
          ]
        }
      },
      {
        "id": "c408ba31-8e6d-4841-9209-4bffb097fe94",
        "name": "aes-generated",
        "providerId": "aes-generated",
        "subComponents": {},
        "config": {
          "priority": [
            "100"
          ]
        }
      }
    ]
  },
  "internationalizationEnabled": false,
  "supportedLocales": [],
  "authenticationFlows": [
    {
      "id": "83aed6b9-b01a-4d0c-8231-0e0d3f36145e",
      "alias": "Account verification options",
      "description": "Method with which to verity the existing account",
      "providerId": "basic-flow",
      "topLevel": false,
      "builtIn": true,
      "authenticationExecutions": [
        {
          "authenticator": "idp-email-verification",
          "authenticatorFlow": false,
          "requirement": "ALTERNATIVE",
          "priority": 10,
          "autheticatorFlow": false,
          "userSetupAllowed": false
        },
        {
          "authenticatorFlow": true,
          "requirement": "ALTERNATIVE",
          "priority": 20,
          "autheticatorFlow": true,
          "flowAlias": "Verify Existing Account by Re-authentication",
          "userSetupAllowed": false
        }
      ]
    },
    {
      "id": "7ba274bb-a510-4896-87d5-4e10f386a205",
      "alias": "Browser - Conditional OTP",
      "description": "Flow to determine if the OTP is required for the authentication",
      "providerId": "basic-flow",
      "topLevel": false,
      "builtIn": true,
      "authenticationExecutions": [
        {
          "authenticator": "conditional-user-configured",
          "authenticatorFlow": false,
          "requirement": "REQUIRED",
          "priority": 10,
          "autheticatorFlow": false,
          "userSetupAllowed": false
        },
        {
          "authenticator": "auth-otp-form",
          "authenticatorFlow": false,
          "requirement": "REQUIRED",
          "priority": 20,
          "autheticatorFlow": false,
          "userSetupAllowed": false
        }
      ]
    },
    {
      "id": "9e83fe7a-945d-475f-9c59-9e9c164da899",
      "alias": "Browser - Conditional Organization",
      "description": "Flow to determine if the organization identity-first login is to be used",
      "providerId": "basic-flow",
      "topLevel": false,
      "builtIn": true,
      "authenticationExecutions": [
        {
          "authenticator": "conditional-user-configured",
          "authenticatorFlow": false,
          "requirement": "REQUIRED",
          "priority": 10,
          "autheticatorFlow": false,
          "userSetupAllowed": false
        },
        {
          "authenticator": "organization",
          "authenticatorFlow": false,
          "requirement": "ALTERNATIVE",
          "priority": 20,
          "autheticatorFlow": false,
          "userSetupAllowed": false
        }
      ]
    },
    {
      "id": "7988717c-5767-462a-acce-bd1d302ecc72",
      "alias": "Direct Grant - Conditional OTP",
      "description": "Flow to determine if the OTP is required for the authentication",
      "providerId": "basic-flow",
      "topLevel": false,
      "builtIn": true,
      "authenticationExecutions": [
        {
          "authenticator": "conditional-user-configured",
          "authenticatorFlow": false,
          "requirement": "REQUIRED",
          "priority": 10,
          "autheticatorFlow": false,
          "userSetupAllowed": false
        },
        {
          "authenticator": "direct-grant-validate-otp",
          "authenticatorFlow": false,
          "requirement": "REQUIRED",
          "priority": 20,
          "autheticatorFlow": false,
          "userSetupAllowed": false
        }
      ]
    },
    {
      "id": "dc6f9f8f-b659-4d7d-84f5-71b0eaf8e271",
      "alias": "First Broker Login - Conditional Organization",
      "description": "Flow to determine if the authenticator that adds organization members is to be used",
      "providerId": "basic-flow",
      "topLevel": false,
      "builtIn": true,
      "authenticationExecutions": [
        {
          "authenticator": "conditional-user-configured",
          "authenticatorFlow": false,
          "requirement": "REQUIRED",
          "priority": 10,
          "autheticatorFlow": false,
          "userSetupAllowed": false
        },
        {
          "authenticator": "idp-add-organization-member",
          "authenticatorFlow": false,
          "requirement": "REQUIRED",
          "priority": 20,
          "autheticatorFlow": false,
          "userSetupAllowed": false
        }
      ]
    },
    {
      "id": "b4d8aa6d-f4a8-44cc-9ea6-6111bb023e13",
      "alias": "First broker login - Conditional OTP",
      "description": "Flow to determine if the OTP is required for the authentication",
      "providerId": "basic-flow",
      "topLevel": false,
      "builtIn": true,
      "authenticationExecutions": [
        {
          "authenticator": "conditional-user-configured",
          "authenticatorFlow": false,
          "requirement": "REQUIRED",
          "priority": 10,
          "autheticatorFlow": false,
          "userSetupAllowed": false
        },
        {
          "authenticator": "auth-otp-form",
          "authenticatorFlow": false,
          "requirement": "REQUIRED",
          "priority": 20,
          "autheticatorFlow": false,
          "userSetupAllowed": false
        }
      ]
    },
    {
      "id": "4f86ea64-c592-46a6-b64a-5f0284f1a0c9",
      "alias": "Handle Existing Account",
      "description": "Handle what to do if there is existing account with same email/username like authenticated identity provider",
      "providerId": "basic-flow",
      "topLevel": false,
      "builtIn": true,
      "authenticationExecutions": [
        {
          "authenticator": "idp-confirm-link",
          "authenticatorFlow": false,
          "requirement": "REQUIRED",
          "priority": 10,
          "autheticatorFlow": false,
          "userSetupAllowed": false
        },
        {
          "authenticatorFlow": true,
          "requirement": "REQUIRED",
          "priority": 20,
          "autheticatorFlow": true,
          "flowAlias": "Account verification options",
          "userSetupAllowed": false
        }
      ]
    },
    {
      "id": "e773ec88-de21-42a3-83a1-ddd306b11d86",
      "alias": "Organization",
      "providerId": "basic-flow",
      "topLevel": false,
      "builtIn": true,
      "authenticationExecutions": [
        {
          "authenticatorFlow": true,
          "requirement": "CONDITIONAL",
          "priority": 10,
          "autheticatorFlow": true,
          "flowAlias": "Browser - Conditional Organization",
          "userSetupAllowed": false
        }
      ]
    },
    {
      "id": "f31a0c10-10c1-46fe-aa1b-2ecbfef7b257",
      "alias": "Reset - Conditional OTP",
      "description": "Flow to determine if the OTP should be reset or not. Set to REQUIRED to force.",
      "providerId": "basic-flow",
      "topLevel": false,
      "builtIn": true,
      "authenticationExecutions": [
        {
          "authenticator": "conditional-user-configured",
          "authenticatorFlow": false,
          "requirement": "REQUIRED",
          "priority": 10,
          "autheticatorFlow": false,
          "userSetupAllowed": false
        },
        {
          "authenticator": "reset-otp",
          "authenticatorFlow": false,
          "requirement": "REQUIRED",
          "priority": 20,
          "autheticatorFlow": false,
          "userSetupAllowed": false
        }
      ]
    },
    {
      "id": "636eebce-4c27-4091-bdcf-462ef2ad8e1d",
      "alias": "User creation or linking",
      "description": "Flow for the existing/non-existing user alternatives",
      "providerId": "basic-flow",
      "topLevel": false,
      "builtIn": true,
      "authenticationExecutions": [
        {
          "authenticatorConfig": "create unique user config",
          "authenticator": "idp-create-user-if-unique",
          "authenticatorFlow": false,
          "requirement": "ALTERNATIVE",
          "priority": 10,
          "autheticatorFlow": false,
          "userSetupAllowed": false
        },
        {
          "authenticatorFlow": true,
          "requirement": "ALTERNATIVE",
          "priority": 20,
          "autheticatorFlow": true,
          "flowAlias": "Handle Existing Account",
          "userSetupAllowed": false
        }
      ]
    },
    {
      "id": "9106bf05-1c47-477a-a412-18ee4e8746c4",
      "alias": "Verify Existing Account by Re-authentication",
      "description": "Reauthentication of existing account",
      "providerId": "basic-flow",
      "topLevel": false,
      "builtIn": true,
      "authenticationExecutions": [
        {
          "authenticator": "idp-username-password-form",
          "authenticatorFlow": false,
          "requirement": "REQUIRED",
          "priority": 10,
          "autheticatorFlow": false,
          "userSetupAllowed": false
        },
        {
          "authenticatorFlow": true,
          "requirement": "CONDITIONAL",
          "priority": 20,
          "autheticatorFlow": true,
          "flowAlias": "First broker login - Conditional OTP",
          "userSetupAllowed": false
        }
      ]
    },
    {
      "id": "f344122e-f79f-4b2a-9c89-945884b0d4cd",
      "alias": "browser",
      "description": "Browser based authentication",
      "providerId": "basic-flow",
      "topLevel": true,
      "builtIn": true,
      "authenticationExecutions": [
        {
          "authenticator": "auth-cookie",
          "authenticatorFlow": false,
          "requirement": "ALTERNATIVE",
          "priority": 10,
          "autheticatorFlow": false,
          "userSetupAllowed": false
        },
        {
          "authenticator": "auth-spnego",
          "authenticatorFlow": false,
          "requirement": "DISABLED",
          "priority": 20,
          "autheticatorFlow": false,
          "userSetupAllowed": false
        },
        {
          "authenticator": "identity-provider-redirector",
          "authenticatorFlow": false,
          "requirement": "ALTERNATIVE",
          "priority": 25,
          "autheticatorFlow": false,
          "userSetupAllowed": false
        },
        {
          "authenticatorFlow": true,
          "requirement": "ALTERNATIVE",
          "priority": 26,
          "autheticatorFlow": true,
          "flowAlias": "Organization",
          "userSetupAllowed": false
        },
        {
          "authenticatorFlow": true,
          "requirement": "ALTERNATIVE",
          "priority": 30,
          "autheticatorFlow": true,
          "flowAlias": "forms",
          "userSetupAllowed": false
        }
      ]
    },
    {
      "id": "fa38353a-8d93-4019-8892-20e174454a89",
      "alias": "clients",
      "description": "Base authentication for clients",
      "providerId": "client-flow",
      "topLevel": true,
      "builtIn": true,
      "authenticationExecutions": [
        {
          "authenticator": "client-secret",
          "authenticatorFlow": false,
          "requirement": "ALTERNATIVE",
          "priority": 10,
          "autheticatorFlow": false,
          "userSetupAllowed": false
        },
        {
          "authenticator": "client-jwt",
          "authenticatorFlow": false,
          "requirement": "ALTERNATIVE",
          "priority": 20,
          "autheticatorFlow": false,
          "userSetupAllowed": false
        },
        {
          "authenticator": "client-secret-jwt",
          "authenticatorFlow": false,
          "requirement": "ALTERNATIVE",
          "priority": 30,
          "autheticatorFlow": false,
          "userSetupAllowed": false
        },
        {
          "authenticator": "client-x509",
          "authenticatorFlow": false,
          "requirement": "ALTERNATIVE",
          "priority": 40,
          "autheticatorFlow": false,
          "userSetupAllowed": false
        }
      ]
    },
    {
      "id": "04c962b5-450d-4265-bec2-a2a70bed63be",
      "alias": "direct grant",
      "description": "OpenID Connect Resource Owner Grant",
      "providerId": "basic-flow",
      "topLevel": true,
      "builtIn": true,
      "authenticationExecutions": [
        {
          "authenticator": "direct-grant-validate-username",
          "authenticatorFlow": false,
          "requirement": "REQUIRED",
          "priority": 10,
          "autheticatorFlow": false,
          "userSetupAllowed": false
        },
        {
          "authenticator": "direct-grant-validate-password",
          "authenticatorFlow": false,
          "requirement": "REQUIRED",
          "priority": 20,
          "autheticatorFlow": false,
          "userSetupAllowed": false
        },
        {
          "authenticatorFlow": true,
          "requirement": "CONDITIONAL",
          "priority": 30,
          "autheticatorFlow": true,
          "flowAlias": "Direct Grant - Conditional OTP",
          "userSetupAllowed": false
        }
      ]
    },
    {
      "id": "da31f4c6-5e56-482d-ad6f-ba94c4f2dd9a",
      "alias": "docker auth",
      "description": "Used by Docker clients to authenticate against the IDP",
      "providerId": "basic-flow",
      "topLevel": true,
      "builtIn": true,
      "authenticationExecutions": [
        {
          "authenticator": "docker-http-basic-authenticator",
          "authenticatorFlow": false,
          "requirement": "REQUIRED",
          "priority": 10,
          "autheticatorFlow": false,
          "userSetupAllowed": false
        }
      ]
    },
    {
      "id": "8217e8a0-23ec-4ea3-917b-e17573f68884",
      "alias": "first broker login",
      "description": "Actions taken after first broker login with identity provider account, which is not yet linked to any Keycloak account",
      "providerId": "basic-flow",
      "topLevel": true,
      "builtIn": true,
      "authenticationExecutions": [
        {
          "authenticatorConfig": "review profile config",
          "authenticator": "idp-review-profile",
          "authenticatorFlow": false,
          "requirement": "REQUIRED",
          "priority": 10,
          "autheticatorFlow": false,
          "userSetupAllowed": false
        },
        {
          "authenticatorFlow": true,
          "requirement": "REQUIRED",
          "priority": 20,
          "autheticatorFlow": true,
          "flowAlias": "User creation or linking",
          "userSetupAllowed": false
        },
        {
          "authenticatorFlow": true,
          "requirement": "CONDITIONAL",
          "priority": 50,
          "autheticatorFlow": true,
          "flowAlias": "First Broker Login - Conditional Organization",
          "userSetupAllowed": false
        }
      ]
    },
    {
      "id": "e6294761-d008-4100-af55-0b10c97fd3fa",
      "alias": "forms",
      "description": "Username, password, otp and other auth forms.",
      "providerId": "basic-flow",
      "topLevel": false,
      "builtIn": true,
      "authenticationExecutions": [
        {
          "authenticator": "auth-username-password-form",
          "authenticatorFlow": false,
          "requirement": "REQUIRED",
          "priority": 10,
          "autheticatorFlow": false,
          "userSetupAllowed": false
        },
        {
          "authenticatorFlow": true,
          "requirement": "CONDITIONAL",
          "priority": 20,
          "autheticatorFlow": true,
          "flowAlias": "Browser - Conditional OTP",
          "userSetupAllowed": false
        }
      ]
    },
    {
      "id": "7866dcc8-11ba-499c-8f37-64456a00cef0",
      "alias": "registration",
      "description": "Registration flow",
      "providerId": "basic-flow",
      "topLevel": true,
      "builtIn": true,
      "authenticationExecutions": [
        {
          "authenticator": "registration-page-form",
          "authenticatorFlow": true,
          "requirement": "REQUIRED",
          "priority": 10,
          "autheticatorFlow": true,
          "flowAlias": "registration form",
          "userSetupAllowed": false
        }
      ]
    },
    {
      "id": "1db01c15-f398-418f-a001-a28800ed99ab",
      "alias": "registration form",
      "description": "Registration form",
      "providerId": "form-flow",
      "topLevel": false,
      "builtIn": true,
      "authenticationExecutions": [
        {
          "authenticator": "registration-user-creation",
          "authenticatorFlow": false,
          "requirement": "REQUIRED",
          "priority": 20,
          "autheticatorFlow": false,
          "userSetupAllowed": false
        },
        {
          "authenticator": "registration-password-action",
          "authenticatorFlow": false,
          "requirement": "REQUIRED",
          "priority": 50,
          "autheticatorFlow": false,
          "userSetupAllowed": false
        },
        {
          "authenticator": "registration-recaptcha-action",
          "authenticatorFlow": false,
          "requirement": "DISABLED",
          "priority": 60,
          "autheticatorFlow": false,
          "userSetupAllowed": false
        },
        {
          "authenticator": "registration-terms-and-conditions",
          "authenticatorFlow": false,
          "requirement": "DISABLED",
          "priority": 70,
          "autheticatorFlow": false,
          "userSetupAllowed": false
        }
      ]
    },
    {
      "id": "96c40ec8-4fa5-4534-8293-de6325db6b18",
      "alias": "reset credentials",
      "description": "Reset credentials for a user if they forgot their password or something",
      "providerId": "basic-flow",
      "topLevel": true,
      "builtIn": true,
      "authenticationExecutions": [
        {
          "authenticator": "reset-credentials-choose-user",
          "authenticatorFlow": false,
          "requirement": "REQUIRED",
          "priority": 10,
          "autheticatorFlow": false,
          "userSetupAllowed": false
        },
        {
          "authenticator": "reset-credential-email",
          "authenticatorFlow": false,
          "requirement": "REQUIRED",
          "priority": 20,
          "autheticatorFlow": false,
          "userSetupAllowed": false
        },
        {
          "authenticator": "reset-password",
          "authenticatorFlow": false,
          "requirement": "REQUIRED",
          "priority": 30,
          "autheticatorFlow": false,
          "userSetupAllowed": false
        },
        {
          "authenticatorFlow": true,
          "requirement": "CONDITIONAL",
          "priority": 40,
          "autheticatorFlow": true,
          "flowAlias": "Reset - Conditional OTP",
          "userSetupAllowed": false
        }
      ]
    },
    {
      "id": "1cf03017-79ea-4626-90ea-7e526d6514d3",
      "alias": "saml ecp",
      "description": "SAML ECP Profile Authentication Flow",
      "providerId": "basic-flow",
      "topLevel": true,
      "builtIn": true,
      "authenticationExecutions": [
        {
          "authenticator": "http-basic-authenticator",
          "authenticatorFlow": false,
          "requirement": "REQUIRED",
          "priority": 10,
          "autheticatorFlow": false,
          "userSetupAllowed": false
        }
      ]
    }
  ],
  "authenticatorConfig": [
    {
      "id": "280adada-8d9d-4ae3-8cab-d9908152cb7a",
      "alias": "create unique user config",
      "config": {
        "require.password.update.after.registration": "false"
      }
    },
    {
      "id": "6168dec5-6678-4b2d-9842-1201884fca7e",
      "alias": "review profile config",
      "config": {
        "update.profile.on.first.login": "missing"
      }
    }
  ],
  "requiredActions": [
    {
      "alias": "CONFIGURE_TOTP",
      "name": "Configure OTP",
      "providerId": "CONFIGURE_TOTP",
      "enabled": true,
      "defaultAction": false,
      "priority": 10,
      "config": {}
    },
    {
      "alias": "TERMS_AND_CONDITIONS",
      "name": "Terms and Conditions",
      "providerId": "TERMS_AND_CONDITIONS",
      "enabled": false,
      "defaultAction": false,
      "priority": 20,
      "config": {}
    },
    {
      "alias": "UPDATE_PASSWORD",
      "name": "Update Password",
      "providerId": "UPDATE_PASSWORD",
      "enabled": true,
      "defaultAction": false,
      "priority": 30,
      "config": {}
    },
    {
      "alias": "UPDATE_PROFILE",
      "name": "Update Profile",
      "providerId": "UPDATE_PROFILE",
      "enabled": true,
      "defaultAction": false,
      "priority": 40,
      "config": {}
    },
    {
      "alias": "VERIFY_EMAIL",
      "name": "Verify Email",
      "providerId": "VERIFY_EMAIL",
      "enabled": true,
      "defaultAction": false,
      "priority": 50,
      "config": {}
    },
    {
      "alias": "delete_account",
      "name": "Delete Account",
      "providerId": "delete_account",
      "enabled": false,
      "defaultAction": false,
      "priority": 60,
      "config": {}
    },
    {
      "alias": "webauthn-register",
      "name": "Webauthn Register",
      "providerId": "webauthn-register",
      "enabled": true,
      "defaultAction": false,
      "priority": 70,
      "config": {}
    },
    {
      "alias": "webauthn-register-passwordless",
      "name": "Webauthn Register Passwordless",
      "providerId": "webauthn-register-passwordless",
      "enabled": true,
      "defaultAction": false,
      "priority": 80,
      "config": {}
    },
    {
      "alias": "VERIFY_PROFILE",
      "name": "Verify Profile",
      "providerId": "VERIFY_PROFILE",
      "enabled": true,
      "defaultAction": false,
      "priority": 90,
      "config": {}
    },
    {
      "alias": "delete_credential",
      "name": "Delete Credential",
      "providerId": "delete_credential",
      "enabled": true,
      "defaultAction": false,
      "priority": 100,
      "config": {}
    },
    {
      "alias": "update_user_locale",
      "name": "Update User Locale",
      "providerId": "update_user_locale",
      "enabled": true,
      "defaultAction": false,
      "priority": 1000,
      "config": {}
    }
  ],
  "browserFlow": "browser",
  "registrationFlow": "registration",
  "directGrantFlow": "direct grant",
  "resetCredentialsFlow": "reset credentials",
  "clientAuthenticationFlow": "clients",
  "dockerAuthenticationFlow": "docker auth",
  "firstBrokerLoginFlow": "first broker login",
  "attributes": {
    "cibaBackchannelTokenDeliveryMode": "poll",
    "cibaExpiresIn": "120",
    "cibaAuthRequestedUserHint": "login_hint",
    "oauth2DeviceCodeLifespan": "600",
    "clientOfflineSessionMaxLifespan": "0",
    "oauth2DevicePollingInterval": "5",
    "clientSessionIdleTimeout": "0",
    "parRequestUriLifespan": "60",
    "clientSessionMaxLifespan": "0",
    "clientOfflineSessionIdleTimeout": "0",
    "cibaInterval": "5",
    "realmReusableOtpCode": "false"
  },
  "keycloakVersion": "26.1.3",
  "userManagedAccessAllowed": false,
  "organizationsEnabled": false,
  "verifiableCredentialsEnabled": false,
  "adminPermissionsEnabled": false,
  "clientProfiles": {
    "profiles": []
  },
  "clientPolicies": {
    "policies": []
  }
}